ALU.sv
module ALU #(
    parameter CONTROL_BITS = 3,
              DATA_WIDTH = 32
)(
    input logic  [CONTROL_BITS-1:0]  alu_control,
    input logic  [DATA_WIDTH-1:0]   operand_a,
    input logic  [DATA_WIDTH-1:0]   operand_b,
    output logic [DATA_WIDTH-1:0]   result,
    output                          result_eq_zero   
);

// assign result_eq_zero = (result == {DATA_WIDTH{1'b0}});     // This needs looking into

always_comb begin
    result = {DATA_WIDTH{1'b0}};
    case (alu_control)
        //the below width casts should work to allow CONTROL_BITS to be changed later on
        //these might need changed if it turns out it doesn't produce the right number
        {CONTROL_BITS'('b000)}: result = operand_a + operand_b; // ADD
        {CONTROL_BITS'('b001)}: result = operand_a - operand_b; // SUBTRACT
        {CONTROL_BITS'('b010)}: result = operand_a & operand_b; // AND
        {CONTROL_BITS'('b011)}: result = operand_a | operand_b; // OR
        // {CONTROL_BITS'('b100)}:
        {CONTROL_BITS'('b101)}: result = {{DATA_WIDTH-1{1'b0}}, operand_a < operand_b}; // SLT
        // {CONTROL_BITS'('b110)}:
        // {CONTROL_BITS'('b111)}:
        3'b110: begin
            if(operand_a == operand_b) result_eq_zero = 1;
            else result_eq_zero = 0;
        end
        default: result = {DATA_WIDTH{1'b0}}; // OUTPUT ZERO

    endcase

end

endmodule

ALU_op2source_mux.sv
module ALU_op2source_mux #(
    parameter DATA_WIDTH = 32
)(
    input logic                   sel,
    input logic  [DATA_WIDTH-1:0] in0,
    input logic  [DATA_WIDTH-1:0] in1,
    output logic [DATA_WIDTH-1:0] out
);

assign out = sel ? in1 : in0;

endmodule

register_file.sv
module register_file #(
    parameter ADDRESS_WIDTH = 5, // 5 bits required to store registers x0 up to x31
              DATA_WIDTH = 32 // each register contains 32 bits
)(
    input logic                     clk,
    input logic                     we3,
    input logic [ADDRESS_WIDTH-1:0] a1, // RD1 address
    input logic [ADDRESS_WIDTH-1:0] a2, // RD2 address
    input logic [ADDRESS_WIDTH-1:0] a3, // WD3 address
    input logic [DATA_WIDTH-1:0]    wd3, // wd3 data input
    output logic [DATA_WIDTH-1:0]   rd1, // rd1 data output
    output logic [DATA_WIDTH-1:0]   rd2,  // rd2 data output
    output logic [DATA_WIDTH-1:0]   a0 // permanent access to x10 register for the purposes of this lab    
);

/* 
create array which essentially is the register file
line below creates an array with (2^ADDRESS_WIDTH)-1 registers each having [DATA_WIDTH-1] bit outputs
in SystemVerilog x**y is x to power of y (can't use ^ for powers as ^ represents XOR)
for parameter defaults address_width = 5 and data_width = 32:
    array created with 32 entries with address bits [4:0], each entry has data bits [31:0]
*/
logic [DATA_WIDTH-1:0] regfile_array [2**ADDRESS_WIDTH-1:0];

// PICK ONE FROM THIS SECTION ====

    // assign all register values to 0
    // initial regfile_array = '{default:0};
  
    // assign register x0 to 0
    initial regfile_array[0] = {DATA_WIDTH{1'b0}};   

// ===============================

// "All read ports in both instruction, register file and data memory are asynchronous
// meaning that the read data is available as soon as the address is presented"
// read logic is therefore combinational

// combinational, asynchronous
// assign read ports
assign rd1 = regfile_array[a1];
assign rd2 = regfile_array[a2];
assign a0 = regfile_array[10]; // a0 output will show contents of x10 register for purposes of this lab

// write assignments happen on positive clock edge
always_ff @(posedge clk) begin
    // if write enabled
    if (we3 == 1'b1)
        // only write if not writing to register x0
        if(a3 != {DATA_WIDTH{1'b0}}) 
            // synchronous assignment of write data input to register specified in a3
            regfile_array[a3] <= wd3;
end

endmodule

sign_extend.sv
module sign_extend #(
    parameter WIDTH = 32
)(  
    // input  logic [WIDTH-1:0]    instr,      
    input   logic [16:0]        instr,
    input  logic                ImmSrc,
    output logic [WIDTH-1:0]    ImmOp
);

always_comb begin
    case(ImmSrc)
        // 1'b0: ImmOp = {{20{instr[31]}}, instr[31:20]};                   // addi
        // 1'b1: ImmOp = {{20{instr[31]}}, instr[7], instr[30:25], instr[11:8], 1'b0};    // branch
        1'b0: ImmOp = {{20{instr[16]}}, instr[16:5]};                                //add
        1'b1: ImmOp = {{20{instr[16]}}, instr[0], instr[15:10], instr[4:1], 1'b0};   //branch
    endcase
end
endmodule

control_unit.sv
module control_unit(
    input  logic        EQ,
    // input  logic [31:0] instr,           
    input logic [9:0]   instr,      // equals {func3, opcode}
    output logic        RegWrite,
    output logic [2:0]  ALUctrl,
    output logic        ALUsrc,
    output logic        ImmSrc,
    output logic        PCsrc     

);

always_comb
    // RegWrite = 0; 
    // ALUctrl = 000; 
    // ALUsrc = 1; 
    // ImmSrc = 0; 
    // PCsrc = 0;

    // inputinstr = {{instr[6:0]}, {instr[14:12]}}
    case(instr)
        10'b0000010011: begin   // addi
            RegWrite = 1;   // Write the result to register
            ALUsrc = 1;     // The second operand for the alu comes from the sign extend unit
            ALUctrl = 3'b000;    // The ALU operation will be an addition
            ImmSrc = 0;     // This tells the sign extend unit that the immediate value will come from {20'b0, instr[31:20]}
            PCsrc = 0;
        end
        10'b0011100011: begin   // bne
            RegWrite = 0;   // The register doens't need to be written to for a bne instruction
            ImmSrc = 1;     // This tells the sign extend unit that the immediate value will come from {19'b0, instr[31], instr[7], instr[30:25], instr[11:8], 1'b0}
            ALUctrl = 3'b110;    // The operation will be a comparison
            ALUsrc = 0;
            if(EQ == 0) PCsrc = 1;  // Since two operands aren't equal we branch
            else PCsrc = 0;
        end
        default: begin
            RegWrite = 0;   // If the instruction is unknown this ensures we don't overwrite the register file
            PCsrc = 0;      // And this ensures that program counter just moves onto the next instruction rather than randomly branching
            ALUctrl = 3'b0;
            ALUsrc = 0;
            ImmSrc = 0;
        end
    endcase
endmodule

instr_mem.sv
module instr_mem  #(
    parameter   ADDRESS_WIDTH = 32,
                DATA_WIDTH = 8
)(
    input  logic [ADDRESS_WIDTH-1:0]    PC,
    output logic [ADDRESS_WIDTH-1:0]    instr
);

logic [DATA_WIDTH-1:0] instr_mem [27:0];

initial begin
        $display("Loading rom.");
        $readmemh("instr_mem.mem", instr_mem);
end;

assign instr = {{instr_mem[PC]}, {instr_mem[PC+1]}, {instr_mem[PC+2]}, {instr_mem[PC+3]}};

endmodule

PC.sv
module PC #(
    parameter WIDTH = 32
)(
    //interface signals
    input logic clk,
    input logic rst,
    input logic [1:0] pcscr,
    input logic [WIDTH-1:0] ImmOp,
    output logic [WIDTH-1:0] count
);

always_ff @ (posedge clk)
    if (rst) count <= {WIDTH{1'b0}};

    else if (pcsrc == 1'b1) count <= count + {ImmOp};
    else if (pcsrc == 1'b0) count <= count + 32'b4;

endmodule

cpu.sv
module cpu #(
    parameter DATA_WIDTH = 32
) (
    input logic         clk,
    input logic         rst,
    output logic [31:0] a0
);

logic [DATA_WIDTH-1:0] pc;
// logic [DATA_WIDTH-1:0] branch_pc;
// logic [DATA_WIDTH-1:0] inc_pc;
// logic [DATA_WIDTH-1:0] next_pc;
logic                  pc_src;
logic [DATA_WIDTH-1:0] instr;
logic                  eq;
logic                  reg_write;
logic [2:0]            alu_ctrl;
logic                  alu_src;
logic                  imm_src;
logic [DATA_WIDTH-1:0] imm_op;
logic [4:0]            rs1;
logic [4:0]            rs2;
logic [4:0]            rd;
logic [DATA_WIDTH-1:0] alu_out;
logic [DATA_WIDTH-1:0] alu_op1;
logic [DATA_WIDTH-1:0] alu_op2;
logic [DATA_WIDTH-1:0] reg_op2;

always_comb begin
    // inc_pc = pc + 4;
    // branch_pc = pc + imm_op;
    // next_pc = pc_src ? branch_pc : inc_pc;
    rs1 = instr[19:15];
    rs2 = instr[24:20];
    rd = instr[11:7];
    // alu_op2 = alu_src ? imm_op : reg_op2;
end

PC pc_section(
    .clk (clk),
    .rst (rst),
    .pcsrc (pc_src),
    .ImmOp (imm_op),
    .count (pc)
);
instr_mem instruction_mem(
    .PC (pc),
    .instr (instr)
);
control_unit contr_unit(
    .EQ (eq),
    .instr ({instr[14:12], instr[6:0]}),
    .RegWrite (reg_write),
    .ALUctrl (alu_ctrl),
    .ALUsrc (alu_src),
    .ImmSrc (imm_src),
    .PCsrc (pc_src)
);
sign_extend sgn_ext(
    .instr ({instr[31:20], instr[11:7]}),
    .ImmSrc (imm_src),
    .ImmOp (imm_op)
);
register_file reg_file(
    .clk (clk),
    .a1 (rs1),
    .a2 (rs2),
    .a3 (rd),
    .we3 (reg_write),
    .wd3 (alu_out),
    .rd1 (alu_op1),
    .rd2 (reg_op2),
    .a0 (a0)
);
ALU_op2source_mux alu_mux(
    .sel (alu_src),
    .in0 (reg_op2),
    .in1 (imm_op),
    .out (alu_op2)
);
ALU alu(
    .operand_a (alu_op1),
    .operand_b (alu_op2),
    .alu_control (alu_ctrl),
    .result (alu_out),
    .result_eq_zero (eq)
);

endmodule

cpu.vcd
$version Generated by VerilatedVcd $end
$date Thu Dec  8 14:14:50 2022 $end
$timescale 1ps $end

 $scope module TOP $end
  $var wire 32 s a0 [31:0] $end
  $var wire  1 q clk $end
  $var wire  1 r rst $end
  $scope module cpu $end
   $var wire 32 t DATA_WIDTH [31:0] $end
   $var wire 32 s a0 [31:0] $end
   $var wire  3 D alu_ctrl [2:0] $end
   $var wire 32 L alu_op1 [31:0] $end
   $var wire 32 M alu_op2 [31:0] $end
   $var wire 32 K alu_out [31:0] $end
   $var wire  1 E alu_src $end
   $var wire  1 q clk $end
   $var wire  1 B eq $end
   $var wire 32 G imm_op [31:0] $end
   $var wire  1 F imm_src $end
   $var wire 32 A instr [31:0] $end
   $var wire 32 ? pc [31:0] $end
   $var wire  1 @ pc_src $end
   $var wire  5 J rd [4:0] $end
   $var wire 32 N reg_op2 [31:0] $end
   $var wire  1 C reg_write $end
   $var wire  5 H rs1 [4:0] $end
   $var wire  5 I rs2 [4:0] $end
   $var wire  1 r rst $end
   $scope module alu $end
    $var wire 32 u CONTROL_BITS [31:0] $end
    $var wire 32 t DATA_WIDTH [31:0] $end
    $var wire  3 D alu_control [2:0] $end
    $var wire 32 L operand_a [31:0] $end
    $var wire 32 M operand_b [31:0] $end
    $var wire 32 K result [31:0] $end
    $var wire  1 B result_eq_zero $end
   $upscope $end
   $scope module alu_mux $end
    $var wire 32 t DATA_WIDTH [31:0] $end
    $var wire 32 N in0 [31:0] $end
    $var wire 32 G in1 [31:0] $end
    $var wire 32 M out [31:0] $end
    $var wire  1 E sel $end
   $upscope $end
   $scope module contr_unit $end
    $var wire  3 D ALUctrl [2:0] $end
    $var wire  1 E ALUsrc $end
    $var wire  1 B EQ $end
    $var wire  1 F ImmSrc $end
    $var wire  1 @ PCsrc $end
    $var wire  1 C RegWrite $end
    $var wire 10 O instr [9:0] $end
   $upscope $end
   $scope module instruction_mem $end
    $var wire 32 t ADDRESS_WIDTH [31:0] $end
    $var wire 32 v DATA_WIDTH [31:0] $end
    $var wire 32 ? PC [31:0] $end
    $var wire 32 A instr [31:0] $end
    $var wire  8 # instr_mem[0] [7:0] $end
    $var wire  8 - instr_mem[10] [7:0] $end
    $var wire  8 . instr_mem[11] [7:0] $end
    $var wire  8 / instr_mem[12] [7:0] $end
    $var wire  8 0 instr_mem[13] [7:0] $end
    $var wire  8 1 instr_mem[14] [7:0] $end
    $var wire  8 2 instr_mem[15] [7:0] $end
    $var wire  8 3 instr_mem[16] [7:0] $end
    $var wire  8 4 instr_mem[17] [7:0] $end
    $var wire  8 5 instr_mem[18] [7:0] $end
    $var wire  8 6 instr_mem[19] [7:0] $end
    $var wire  8 $ instr_mem[1] [7:0] $end
    $var wire  8 7 instr_mem[20] [7:0] $end
    $var wire  8 8 instr_mem[21] [7:0] $end
    $var wire  8 9 instr_mem[22] [7:0] $end
    $var wire  8 : instr_mem[23] [7:0] $end
    $var wire  8 ; instr_mem[24] [7:0] $end
    $var wire  8 < instr_mem[25] [7:0] $end
    $var wire  8 = instr_mem[26] [7:0] $end
    $var wire  8 > instr_mem[27] [7:0] $end
    $var wire  8 % instr_mem[2] [7:0] $end
    $var wire  8 & instr_mem[3] [7:0] $end
    $var wire  8 ' instr_mem[4] [7:0] $end
    $var wire  8 ( instr_mem[5] [7:0] $end
    $var wire  8 ) instr_mem[6] [7:0] $end
    $var wire  8 * instr_mem[7] [7:0] $end
    $var wire  8 + instr_mem[8] [7:0] $end
    $var wire  8 , instr_mem[9] [7:0] $end
   $upscope $end
   $scope module pc_section $end
    $var wire 32 G ImmOp [31:0] $end
    $var wire 32 t WIDTH [31:0] $end
    $var wire  1 q clk $end
    $var wire 32 ? count [31:0] $end
    $var wire  1 @ pcsrc $end
    $var wire  1 r rst $end
   $upscope $end
   $scope module reg_file $end
    $var wire 32 w ADDRESS_WIDTH [31:0] $end
    $var wire 32 t DATA_WIDTH [31:0] $end
    $var wire 32 s a0 [31:0] $end
    $var wire  5 H a1 [4:0] $end
    $var wire  5 I a2 [4:0] $end
    $var wire  5 J a3 [4:0] $end
    $var wire  1 q clk $end
    $var wire 32 L rd1 [31:0] $end
    $var wire 32 N rd2 [31:0] $end
    $var wire 32 P regfile_array[0] [31:0] $end
    $var wire 32 Z regfile_array[10] [31:0] $end
    $var wire 32 [ regfile_array[11] [31:0] $end
    $var wire 32 \ regfile_array[12] [31:0] $end
    $var wire 32 ] regfile_array[13] [31:0] $end
    $var wire 32 ^ regfile_array[14] [31:0] $end
    $var wire 32 _ regfile_array[15] [31:0] $end
    $var wire 32 ` regfile_array[16] [31:0] $end
    $var wire 32 a regfile_array[17] [31:0] $end
    $var wire 32 b regfile_array[18] [31:0] $end
    $var wire 32 c regfile_array[19] [31:0] $end
    $var wire 32 Q regfile_array[1] [31:0] $end
    $var wire 32 d regfile_array[20] [31:0] $end
    $var wire 32 e regfile_array[21] [31:0] $end
    $var wire 32 f regfile_array[22] [31:0] $end
    $var wire 32 g regfile_array[23] [31:0] $end
    $var wire 32 h regfile_array[24] [31:0] $end
    $var wire 32 i regfile_array[25] [31:0] $end
    $var wire 32 j regfile_array[26] [31:0] $end
    $var wire 32 k regfile_array[27] [31:0] $end
    $var wire 32 l regfile_array[28] [31:0] $end
    $var wire 32 m regfile_array[29] [31:0] $end
    $var wire 32 R regfile_array[2] [31:0] $end
    $var wire 32 n regfile_array[30] [31:0] $end
    $var wire 32 o regfile_array[31] [31:0] $end
    $var wire 32 S regfile_array[3] [31:0] $end
    $var wire 32 T regfile_array[4] [31:0] $end
    $var wire 32 U regfile_array[5] [31:0] $end
    $var wire 32 V regfile_array[6] [31:0] $end
    $var wire 32 W regfile_array[7] [31:0] $end
    $var wire 32 X regfile_array[8] [31:0] $end
    $var wire 32 Y regfile_array[9] [31:0] $end
    $var wire 32 K wd3 [31:0] $end
    $var wire  1 C we3 $end
   $upscope $end
   $scope module sgn_ext $end
    $var wire 32 G ImmOp [31:0] $end
    $var wire  1 F ImmSrc $end
    $var wire 32 t WIDTH [31:0] $end
    $var wire 17 p instr [16:0] $end
   $upscope $end
  $upscope $end
 $upscope $end
$enddefinitions $end


#0
b00000000 #
b00000000 $
b00000000 %
b00000000 &
b00000000 '
b00000000 (
b00000000 )
b00000000 *
b00000000 +
b00000000 ,
b00000000 -
b00000000 .
b00000000 /
b00000000 0
b00000000 1
b00000000 2
b00000000 3
b00000000 4
b00000000 5
b00000000 6
b00000000 7
b00000000 8
b00000000 9
b00000000 :
b00000000 ;
b00000000 <
b00000000 =
b00000000 >
b00000000000000000000000000000000 ?
0@
b00000000000000000000000000000000 A
0B
0C
b000 D
0E
0F
b00000000000000000000000000000000 G
b00000 H
b00000 I
b00000 J
b00000000000000000000000000000000 K
b00000000000000000000000000000000 L
b00000000000000000000000000000000 M
b00000000000000000000000000000000 N
b0000000000 O
b00000000000000000000000000000000 P
b00000000000000000000000000000000 Q
b00000000000000000000000000000000 R
b00000000000000000000000000000000 S
b00000000000000000000000000000000 T
b00000000000000000000000000000000 U
b00000000000000000000000000000000 V
b00000000000000000000000000000000 W
b00000000000000000000000000000000 X
b00000000000000000000000000000000 Y
b00000000000000000000000000000000 Z
b00000000000000000000000000000000 [
b00000000000000000000000000000000 \
b00000000000000000000000000000000 ]
b00000000000000000000000000000000 ^
b00000000000000000000000000000000 _
b00000000000000000000000000000000 `
b00000000000000000000000000000000 a
b00000000000000000000000000000000 b
b00000000000000000000000000000000 c
b00000000000000000000000000000000 d
b00000000000000000000000000000000 e
b00000000000000000000000000000000 f
b00000000000000000000000000000000 g
b00000000000000000000000000000000 h
b00000000000000000000000000000000 i
b00000000000000000000000000000000 j
b00000000000000000000000000000000 k
b00000000000000000000000000000000 l
b00000000000000000000000000000000 m
b00000000000000000000000000000000 n
b00000000000000000000000000000000 o
b00000000000000000 p
1q
0r
b00000000000000000000000000000000 s
b00000000000000000000000000100000 t
b00000000000000000000000000000011 u
b00000000000000000000000000001000 v
b00000000000000000000000000000101 w
#1
b00001111 #
b11110000 $
b00000011 %
b00010011 &
b00000101 )
b00010011 *
b00000101 -
b10010011 .
b00000101 0
b10000101 1
b00010011 2
b00010101 4
b10000101 5
b10010011 6
b11111110 7
b01100101 8
b10011100 9
b11100011 :
b11111110 ;
b00000011 <
b00011000 =
b00001111111100000000001100010011 A
1C
1E
b00000000000000000000000011111111 G
b11111 I
b00110 J
b00000000000000000000000011111111 K
b00000000000000000000000011111111 M
b0000010011 O
b00001111111100110 p
0q
#2
b00000000000000000000000000000100 ?
b00000000000000000000010100010011 A
b00000000000000000000000000000000 G
b00000 I
b01010 J
b00000000000000000000000000000000 K
b00000000000000000000000000000000 M
b00000000000000000000000011111111 V
b00000000000001010 p
1q
#3
0q
#4
b00000000000000000000000000001000 ?
b00000000000000000000010110010011 A
b01011 J
b00000000000001011 p
1q
#5
0q
#6
b00000000000000000000000000001100 ?
b00000000000001011000010100010011 A
b01011 H
b01010 J
b00000000000001010 p
1q
#7
0q
#8
b00000000000000000000000000010000 ?
b00000000000101011000010110010011 A
b00000000000000000000000000000001 G
b00001 I
b01011 J
b00000000000000000000000000000001 K
b00000000000000000000000000000001 M
b00000000000101011 p
1q
#9
0q
#10
b00000000000000000000000000010100 ?
1@
b11111110011001011001110011100011 A
0C
b110 D
0E
1F
b11111111111111111111111111111000 G
b00110 I
b11001 J
b00000000000000000000000000000000 K
b00000000000000000000000000000001 L
b00000000000000000000000011111111 M
b00000000000000000000000011111111 N
b0011100011 O
b00000000000000000000000000000001 [
b11111110011011001 p
1q
#11
0q
#12
b00000000000000000000000000001100 ?
0@
b00000000000001011000010100010011 A
1C
b000 D
1E
0F
b00000000000000000000000000000000 G
b00000 I
b01010 J
b00000000000000000000000000000001 K
b00000000000000000000000000000000 M
b00000000000000000000000000000000 N
b0000010011 O
b00000000000001010 p
1q
#13
0q
#14
b00000000000000000000000000010000 ?
b00000000000101011000010110010011 A
b00000000000000000000000000000001 G
b00001 I
b01011 J
b00000000000000000000000000000010 K
b00000000000000000000000000000001 M
b00000000000000000000000000000001 Z
b00000000000101011 p
1q
b00000000000000000000000000000001 s
#15
0q
#16
b00000000000000000000000000010100 ?
1@
b11111110011001011001110011100011 A
0C
b110 D
0E
1F
b11111111111111111111111111111000 G
b00110 I
b11001 J
b00000000000000000000000000000000 K
b00000000000000000000000000000010 L
b00000000000000000000000011111111 M
b00000000000000000000000011111111 N
b0011100011 O
b00000000000000000000000000000010 [
b11111110011011001 p
1q
#17
0q
#18
b00000000000000000000000000001100 ?
0@
b00000000000001011000010100010011 A
1C
b000 D
1E
0F
b00000000000000000000000000000000 G
b00000 I
b01010 J
b00000000000000000000000000000010 K
b00000000000000000000000000000000 M
b00000000000000000000000000000000 N
b0000010011 O
b00000000000001010 p
1q
#19
0q
#20
b00000000000000000000000000010000 ?
b00000000000101011000010110010011 A
b00000000000000000000000000000001 G
b00001 I
b01011 J
b00000000000000000000000000000011 K
b00000000000000000000000000000001 M
b00000000000000000000000000000010 Z
b00000000000101011 p
1q
b00000000000000000000000000000010 s
#21
0q
#22
b00000000000000000000000000010100 ?
1@
b11111110011001011001110011100011 A
0C
b110 D
0E
1F
b11111111111111111111111111111000 G
b00110 I
b11001 J
b00000000000000000000000000000000 K
b00000000000000000000000000000011 L
b00000000000000000000000011111111 M
b00000000000000000000000011111111 N
b0011100011 O
b00000000000000000000000000000011 [
b11111110011011001 p
1q
#23
0q
#24
b00000000000000000000000000001100 ?
0@
b00000000000001011000010100010011 A
1C
b000 D
1E
0F
b00000000000000000000000000000000 G
b00000 I
b01010 J
b00000000000000000000000000000011 K
b00000000000000000000000000000000 M
b00000000000000000000000000000000 N
b0000010011 O
b00000000000001010 p
1q
#25
0q
#26
b00000000000000000000000000010000 ?
b00000000000101011000010110010011 A
b00000000000000000000000000000001 G
b00001 I
b01011 J
b00000000000000000000000000000100 K
b00000000000000000000000000000001 M
b00000000000000000000000000000011 Z
b00000000000101011 p
1q
b00000000000000000000000000000011 s
#27
0q
#28
b00000000000000000000000000010100 ?
1@
b11111110011001011001110011100011 A
0C
b110 D
0E
1F
b11111111111111111111111111111000 G
b00110 I
b11001 J
b00000000000000000000000000000000 K
b00000000000000000000000000000100 L
b00000000000000000000000011111111 M
b00000000000000000000000011111111 N
b0011100011 O
b00000000000000000000000000000100 [
b11111110011011001 p
1q
#29
0q
#30
b00000000000000000000000000001100 ?
0@
b00000000000001011000010100010011 A
1C
b000 D
1E
0F
b00000000000000000000000000000000 G
b00000 I
b01010 J
b00000000000000000000000000000100 K
b00000000000000000000000000000000 M
b00000000000000000000000000000000 N
b0000010011 O
b00000000000001010 p
1q
#31
0q
#32
b00000000000000000000000000010000 ?
b00000000000101011000010110010011 A
b00000000000000000000000000000001 G
b00001 I
b01011 J
b00000000000000000000000000000101 K
b00000000000000000000000000000001 M
b00000000000000000000000000000100 Z
b00000000000101011 p
1q
b00000000000000000000000000000100 s
#33
0q
#34
b00000000000000000000000000010100 ?
1@
b11111110011001011001110011100011 A
0C
b110 D
0E
1F
b11111111111111111111111111111000 G
b00110 I
b11001 J
b00000000000000000000000000000000 K
b00000000000000000000000000000101 L
b00000000000000000000000011111111 M
b00000000000000000000000011111111 N
b0011100011 O
b00000000000000000000000000000101 [
b11111110011011001 p
1q
#35
0q
#36
b00000000000000000000000000001100 ?
0@
b00000000000001011000010100010011 A
1C
b000 D
1E
0F
b00000000000000000000000000000000 G
b00000 I
b01010 J
b00000000000000000000000000000101 K
b00000000000000000000000000000000 M
b00000000000000000000000000000000 N
b0000010011 O
b00000000000001010 p
1q
#37
0q
#38
b00000000000000000000000000010000 ?
b00000000000101011000010110010011 A
b00000000000000000000000000000001 G
b00001 I
b01011 J
b00000000000000000000000000000110 K
b00000000000000000000000000000001 M
b00000000000000000000000000000101 Z
b00000000000101011 p
1q
b00000000000000000000000000000101 s
#39
0q
#40
b00000000000000000000000000010100 ?
1@
b11111110011001011001110011100011 A
0C
b110 D
0E
1F
b11111111111111111111111111111000 G
b00110 I
b11001 J
b00000000000000000000000000000000 K
b00000000000000000000000000000110 L
b00000000000000000000000011111111 M
b00000000000000000000000011111111 N
b0011100011 O
b00000000000000000000000000000110 [
b11111110011011001 p
1q
#41
0q
#42
b00000000000000000000000000001100 ?
0@
b00000000000001011000010100010011 A
1C
b000 D
1E
0F
b00000000000000000000000000000000 G
b00000 I
b01010 J
b00000000000000000000000000000110 K
b00000000000000000000000000000000 M
b00000000000000000000000000000000 N
b0000010011 O
b00000000000001010 p
1q
#43
0q
#44
b00000000000000000000000000010000 ?
b00000000000101011000010110010011 A
b00000000000000000000000000000001 G
b00001 I
b01011 J
b00000000000000000000000000000111 K
b00000000000000000000000000000001 M
b00000000000000000000000000000110 Z
b00000000000101011 p
1q
b00000000000000000000000000000110 s
#45
0q
#46
b00000000000000000000000000010100 ?
1@
b11111110011001011001110011100011 A
0C
b110 D
0E
1F
b11111111111111111111111111111000 G
b00110 I
b11001 J
b00000000000000000000000000000000 K
b00000000000000000000000000000111 L
b00000000000000000000000011111111 M
b00000000000000000000000011111111 N
b0011100011 O
b00000000000000000000000000000111 [
b11111110011011001 p
1q
#47
0q
#48
b00000000000000000000000000001100 ?
0@
b00000000000001011000010100010011 A
1C
b000 D
1E
0F
b00000000000000000000000000000000 G
b00000 I
b01010 J
b00000000000000000000000000000111 K
b00000000000000000000000000000000 M
b00000000000000000000000000000000 N
b0000010011 O
b00000000000001010 p
1q
#49
0q
#50
b00000000000000000000000000010000 ?
b00000000000101011000010110010011 A
b00000000000000000000000000000001 G
b00001 I
b01011 J
b00000000000000000000000000001000 K
b00000000000000000000000000000001 M
b00000000000000000000000000000111 Z
b00000000000101011 p
1q
b00000000000000000000000000000111 s
#51
0q
#52
b00000000000000000000000000010100 ?
1@
b11111110011001011001110011100011 A
0C
b110 D
0E
1F
b11111111111111111111111111111000 G
b00110 I
b11001 J
b00000000000000000000000000000000 K
b00000000000000000000000000001000 L
b00000000000000000000000011111111 M
b00000000000000000000000011111111 N
b0011100011 O
b00000000000000000000000000001000 [
b11111110011011001 p
1q
#53
0q
#54
b00000000000000000000000000001100 ?
0@
b00000000000001011000010100010011 A
1C
b000 D
1E
0F
b00000000000000000000000000000000 G
b00000 I
b01010 J
b00000000000000000000000000001000 K
b00000000000000000000000000000000 M
b00000000000000000000000000000000 N
b0000010011 O
b00000000000001010 p
1q
#55
0q
#56
b00000000000000000000000000010000 ?
b00000000000101011000010110010011 A
b00000000000000000000000000000001 G
b00001 I
b01011 J
b00000000000000000000000000001001 K
b00000000000000000000000000000001 M
b00000000000000000000000000001000 Z
b00000000000101011 p
1q
b00000000000000000000000000001000 s
#57
0q
#58
b00000000000000000000000000010100 ?
1@
b11111110011001011001110011100011 A
0C
b110 D
0E
1F
b11111111111111111111111111111000 G
b00110 I
b11001 J
b00000000000000000000000000000000 K
b00000000000000000000000000001001 L
b00000000000000000000000011111111 M
b00000000000000000000000011111111 N
b0011100011 O
b00000000000000000000000000001001 [
b11111110011011001 p
1q
#59
0q
#60
b00000000000000000000000000001100 ?
0@
b00000000000001011000010100010011 A
1C
b000 D
1E
0F
b00000000000000000000000000000000 G
b00000 I
b01010 J
b00000000000000000000000000001001 K
b00000000000000000000000000000000 M
b00000000000000000000000000000000 N
b0000010011 O
b00000000000001010 p
1q
#61
0q
#62
b00000000000000000000000000010000 ?
b00000000000101011000010110010011 A
b00000000000000000000000000000001 G
b00001 I
b01011 J
b00000000000000000000000000001010 K
b00000000000000000000000000000001 M
b00000000000000000000000000001001 Z
b00000000000101011 p
1q
b00000000000000000000000000001001 s
#63
0q
#64
b00000000000000000000000000010100 ?
1@
b11111110011001011001110011100011 A
0C
b110 D
0E
1F
b11111111111111111111111111111000 G
b00110 I
b11001 J
b00000000000000000000000000000000 K
b00000000000000000000000000001010 L
b00000000000000000000000011111111 M
b00000000000000000000000011111111 N
b0011100011 O
b00000000000000000000000000001010 [
b11111110011011001 p
1q
#65
0q
#66
b00000000000000000000000000001100 ?
0@
b00000000000001011000010100010011 A
1C
b000 D
1E
0F
b00000000000000000000000000000000 G
b00000 I
b01010 J
b00000000000000000000000000001010 K
b00000000000000000000000000000000 M
b00000000000000000000000000000000 N
b0000010011 O
b00000000000001010 p
1q
#67
0q
#68
b00000000000000000000000000010000 ?
b00000000000101011000010110010011 A
b00000000000000000000000000000001 G
b00001 I
b01011 J
b00000000000000000000000000001011 K
b00000000000000000000000000000001 M
b00000000000000000000000000001010 Z
b00000000000101011 p
1q
b00000000000000000000000000001010 s
#69
0q
#70
b00000000000000000000000000010100 ?
1@
b11111110011001011001110011100011 A
0C
b110 D
0E
1F
b11111111111111111111111111111000 G
b00110 I
b11001 J
b00000000000000000000000000000000 K
b00000000000000000000000000001011 L
b00000000000000000000000011111111 M
b00000000000000000000000011111111 N
b0011100011 O
b00000000000000000000000000001011 [
b11111110011011001 p
1q
#71
0q
#72
b00000000000000000000000000001100 ?
0@
b00000000000001011000010100010011 A
1C
b000 D
1E
0F
b00000000000000000000000000000000 G
b00000 I
b01010 J
b00000000000000000000000000001011 K
b00000000000000000000000000000000 M
b00000000000000000000000000000000 N
b0000010011 O
b00000000000001010 p
1q
#73
0q
#74
b00000000000000000000000000010000 ?
b00000000000101011000010110010011 A
b00000000000000000000000000000001 G
b00001 I
b01011 J
b00000000000000000000000000001100 K
b00000000000000000000000000000001 M
b00000000000000000000000000001011 Z
b00000000000101011 p
1q
b00000000000000000000000000001011 s
#75
0q
#76
b00000000000000000000000000010100 ?
1@
b11111110011001011001110011100011 A
0C
b110 D
0E
1F
b11111111111111111111111111111000 G
b00110 I
b11001 J
b00000000000000000000000000000000 K
b00000000000000000000000000001100 L
b00000000000000000000000011111111 M
b00000000000000000000000011111111 N
b0011100011 O
b00000000000000000000000000001100 [
b11111110011011001 p
1q
#77
0q
#78
b00000000000000000000000000001100 ?
0@
b00000000000001011000010100010011 A
1C
b000 D
1E
0F
b00000000000000000000000000000000 G
b00000 I
b01010 J
b00000000000000000000000000001100 K
b00000000000000000000000000000000 M
b00000000000000000000000000000000 N
b0000010011 O
b00000000000001010 p
1q
#79
0q
#80
b00000000000000000000000000010000 ?
b00000000000101011000010110010011 A
b00000000000000000000000000000001 G
b00001 I
b01011 J
b00000000000000000000000000001101 K
b00000000000000000000000000000001 M
b00000000000000000000000000001100 Z
b00000000000101011 p
1q
b00000000000000000000000000001100 s
#81
0q
#82
b00000000000000000000000000010100 ?
1@
b11111110011001011001110011100011 A
0C
b110 D
0E
1F
b11111111111111111111111111111000 G
b00110 I
b11001 J
b00000000000000000000000000000000 K
b00000000000000000000000000001101 L
b00000000000000000000000011111111 M
b00000000000000000000000011111111 N
b0011100011 O
b00000000000000000000000000001101 [
b11111110011011001 p
1q
#83
0q
#84
b00000000000000000000000000001100 ?
0@
b00000000000001011000010100010011 A
1C
b000 D
1E
0F
b00000000000000000000000000000000 G
b00000 I
b01010 J
b00000000000000000000000000001101 K
b00000000000000000000000000000000 M
b00000000000000000000000000000000 N
b0000010011 O
b00000000000001010 p
1q
#85
0q
